{"image": "3218.png", "category": "16-19", "gender": "男"}
{"image": "3219.png", "category": "20-24", "gender": "男"}
{"image": "322.png", "category": "16-19", "gender": "男"}
{"image": "3220.png", "category": "20-24", "gender": "男"}
{"image": "3221.png", "category": "20-24", "gender": "男"}
{"image": "3222.png", "category": "16-19", "gender": "男"}
{"image": "3223.png", "category": "20-24", "gender": "男"}
{"image": "3224.png", "category": "20-24", "gender": "男"}
{"image": "3225.png", "category": "16-19", "gender": "男"}
{"image": "3226.png", "category": "20-24", "gender": "男"}
{"image": "3227.png", "category": "16-19", "gender": "男"}
{"image": "3228.png", "category": "20-24", "gender": "男"}
{"image": "3229.png", "category": "20-24", "gender": "男"}
{"image": "323.png", "category": "20-24", "gender": "男"}
{"image": "3230.png", "category": "13-15", "gender": "男"}
{"image": "3231.png", "category": "13-15", "gender": "男"}
{"image": "3232.png", "category": "20-24", "gender": "男"}
{"image": "3233.png", "category": "20-24", "gender": "男"}
{"image": "3234.png", "category": "20-24", "gender": "男"}
{"image": "3235.png", "category": "16-19", "gender": "男"}
{"image": "3236.png", "category": "16-19", "gender": "男"}
{"image": "3237.png", "category": "16-19", "gender": "男"}
{"image": "3238.png", "category": "13-15", "gender": "男"}
{"image": "3239.png", "category": "13-15", "gender": "男"}
{"image": "324.png", "category": "20-24", "gender": "男"}
{"image": "3240.png", "category": "16-19", "gender": "男"}
{"image": "3241.png", "category": "13-15", "gender": "男"}
{"image": "3242.png", "category": "25-30", "gender": "男"}
{"image": "3243.png", "category": "35-40", "gender": "男"}
{"image": "3244.png", "category": "11-12", "gender": "男"}
{"image": "3245.png", "category": "25-30", "gender": "男"}
{"image": "3246.png", "category": "20-24", "gender": "男"}
{"image": "3247.png", "category": "20-24", "gender": "男"}
{"image": "3248.png", "category": "20-24", "gender": "男"}
{"image": "3249.png", "category": "20-24", "gender": "男"}
{"image": "325.png", "category": "16-19", "gender": "男"}
{"image": "3250.png", "category": "16-19", "gender": "男"}
{"image": "3251.png", "category": "16-19", "gender": "男"}
{"image": "3252.png", "category": "16-19", "gender": "男"}
{"image": "3253.png", "category": "16-19", "gender": "男"}
{"image": "3254.png", "category": "13-15", "gender": "男"}
{"image": "3255.png", "category": "16-19", "gender": "男"}
{"image": "3256.png", "category": "11-12", "gender": "男"}
{"image": "3257.png", "category": "11-12", "gender": "男"}
{"image": "3258.png", "category": "11-12", "gender": "男"}
{"image": "3259.png", "category": "20-24", "gender": "男"}
{"image": "326.png", "category": "16-19", "gender": "男"}
{"image": "3260.png", "category": "20-24", "gender": "男"}
{"image": "3261.png", "category": "20-24", "gender": "男"}
{"image": "3262.png", "category": "16-19", "gender": "男"}
{"image": "3263.png", "category": "20-24", "gender": "男"}
{"image": "3264.png", "category": "20-24", "gender": "男"}
{"image": "3265.png", "category": "20-24", "gender": "男"}
{"image": "3266.png", "category": "16-19", "gender": "男"}
{"image": "3267.png", "category": "13-15", "gender": "男"}
{"image": "3268.png", "category": "13-15", "gender": "男"}
{"image": "3269.png", "category": "20-24", "gender": "男"}
{"image": "327.png", "category": "20-24", "gender": "男"}
{"image": "3270.png", "category": "20-24", "gender": "男"}
{"image": "3271.png", "category": "20-24", "gender": "男"}
{"image": "3272.png", "category": "20-24", "gender": "男"}
{"image": "3273.png", "category": "20-24", "gender": "男"}
{"image": "3274.png", "category": "11-12", "gender": "男"}
{"image": "3275.png", "category": "13-15", "gender": "男"}
{"image": "3276.png", "category": "13-15", "gender": "男"}
{"image": "3277.png", "category": "13-15", "gender": "男"}
{"image": "3278.png", "category": "16-19", "gender": "男"}
{"image": "3279.png", "category": "bug", "gender": null}
{"image": "328.png", "category": "20-24", "gender": "男"}
{"image": "3280.png", "category": "20-24", "gender": "男"}
{"image": "3281.png", "category": "20-24", "gender": "男"}
{"image": "3282.png", "category": "20-24", "gender": "男"}
{"image": "3283.png", "category": "20-24", "gender": "男"}
{"image": "3284.png", "category": "16-19", "gender": "男"}
{"image": "3285.png", "category": "20-24", "gender": "男"}
{"image": "3286.png", "category": "20-24", "gender": "男"}
{"image": "3287.png", "category": "16-19", "gender": "男"}
{"image": "3288.png", "category": "13-15", "gender": "男"}
{"image": "3289.png", "category": "13-15", "gender": "男"}
{"image": "329.png", "category": "13-15", "gender": "男"}
{"image": "3290.png", "category": "11-12", "gender": "男"}
{"image": "3291.png", "category": "11-12", "gender": "男"}
{"image": "3292.png", "category": "11-12", "gender": "男"}
{"image": "3293.png", "category": "13-15", "gender": "男"}
{"image": "3294.png", "category": "13-15", "gender": "男"}
{"image": "3295.png", "category": "13-15", "gender": "男"}
{"image": "3296.png", "category": "13-15", "gender": "男"}
{"image": "3297.png", "category": "13-15", "gender": "男"}
{"image": "3298.png", "category": "20-24", "gender": "男"}
{"image": "3299.png", "category": "16-19", "gender": "男"}
{"image": "33.png", "category": "13-15", "gender": "男"}
{"image": "330.png", "category": "16-19", "gender": "男"}
{"image": "3300.png", "category": "16-19", "gender": "男"}
{"image": "3301.png", "category": "13-15", "gender": "男"}
{"image": "3302.png", "category": "20-24", "gender": "男"}
{"image": "3303.png", "category": "20-24", "gender": "男"}
{"image": "3304.png", "category": "20-24", "gender": "男"}
{"image": "3305.png", "category": "20-24", "gender": "男"}
{"image": "3306.png", "category": "20-24", "gender": "男"}
{"image": "3307.png", "category": "13-15", "gender": "男"}
{"image": "3308.png", "category": "13-15", "gender": "男"}
{"image": "3309.png", "category": "13-15", "gender": "男"}
{"image": "331.png", "category": "20-24", "gender": "男"}
{"image": "3310.png", "category": "13-15", "gender": "男"}
{"image": "3311.png", "category": "16-19", "gender": "男"}
{"image": "3312.png", "category": "16-19", "gender": "男"}
{"image": "3313.png", "category": "16-19", "gender": "男"}
{"image": "3314.png", "category": "16-19", "gender": "男"}
{"image": "3315.png", "category": "16-19", "gender": "男"}
{"image": "3316.png", "category": "13-15", "gender": "男"}
{"image": "3317.png", "category": "16-19", "gender": "男"}
{"image": "3318.png", "category": "16-19", "gender": "男"}
{"image": "3319.png", "category": "13-15", "gender": "男"}
{"image": "332.png", "category": "20-24", "gender": "男"}
{"image": "3320.png", "category": "20-24", "gender": "男"}
{"image": "3321.png", "category": "13-15", "gender": "男"}
{"image": "3322.png", "category": "13-15", "gender": "男"}
{"image": "3323.png", "category": "16-19", "gender": "男"}
{"image": "3324.png", "category": "16-19", "gender": "男"}
{"image": "3325.png", "category": "16-19", "gender": "男"}
{"image": "3326.png", "category": "16-19", "gender": "男"}
{"image": "3327.png", "category": "16-19", "gender": "男"}
{"image": "3328.png", "category": "16-19", "gender": "男"}
{"image": "3329.png", "category": "bug", "gender": null}
{"image": "333.png", "category": "20-24", "gender": "男"}
{"image": "3330.png", "category": "13-15", "gender": "男"}
{"image": "3331.png", "category": "16-19", "gender": "男"}
{"image": "3332.png", "category": "16-19", "gender": "男"}
{"image": "3333.png", "category": "25-30", "gender": "男"}
{"image": "3334.png", "category": "25-30", "gender": "男"}
{"image": "3335.png", "category": "25-30", "gender": "男"}
{"image": "3336.png", "category": "20-24", "gender": "男"}
{"image": "3337.png", "category": "20-24", "gender": "男"}
{"image": "3338.png", "category": "20-24", "gender": "男"}
{"image": "3339.png", "category": "16-19", "gender": "男"}
{"image": "334.png", "category": "20-24", "gender": "男"}
{"image": "3340.png", "category": "16-19", "gender": "男"}
{"image": "3341.png", "category": "16-19", "gender": "男"}
{"image": "3342.png", "category": "16-19", "gender": "男"}
{"image": "3343.png", "category": "16-19", "gender": "男"}
{"image": "3344.png", "category": "16-19", "gender": "男"}
{"image": "3345.png", "category": "16-19", "gender": "男"}
{"image": "3346.png", "category": "16-19", "gender": "男"}
{"image": "3347.png", "category": "13-15", "gender": "男"}
{"image": "3348.png", "category": "13-15", "gender": "男"}
{"image": "3349.png", "category": "16-19", "gender": "男"}
{"image": "335.png", "category": "25-30", "gender": "男"}
{"image": "3350.png", "category": "16-19", "gender": "男"}
{"image": "3351.png", "category": "13-15", "gender": "男"}
{"image": "3352.png", "category": "13-15", "gender": "男"}
{"image": "3353.png", "category": "13-15", "gender": "男"}
{"image": "3354.png", "category": "16-19", "gender": "男"}
{"image": "3355.png", "category": "16-19", "gender": "男"}
{"image": "3356.png", "category": "16-19", "gender": "男"}
{"image": "3357.png", "category": "16-19", "gender": "男"}
{"image": "3358.png", "category": "16-19", "gender": "男"}
{"image": "3359.png", "category": "16-19", "gender": "男"}
{"image": "336.png", "category": "25-30", "gender": "男"}
{"image": "3360.png", "category": "20-24", "gender": "男"}
{"image": "3361.png", "category": "20-24", "gender": "男"}
{"image": "3362.png", "category": "16-19", "gender": "男"}
{"image": "3363.png", "category": "20-24", "gender": "男"}
{"image": "3364.png", "category": "25-30", "gender": "男"}
{"image": "3365.png", "category": "20-24", "gender": "男"}
{"image": "3366.png", "category": "bug", "gender": null}
{"image": "3367.png", "category": "25-30", "gender": "男"}
{"image": "3368.png", "category": "16-19", "gender": "男"}
{"image": "3369.png", "category": "16-19", "gender": "男"}
{"image": "337.png", "category": "13-15", "gender": "男"}
{"image": "3370.png", "category": "16-19", "gender": "男"}
{"image": "3371.png", "category": "16-19", "gender": "男"}
{"image": "3372.png", "category": "20-24", "gender": "男"}
{"image": "3373.png", "category": "20-24", "gender": "男"}
{"image": "3374.png", "category": "13-15", "gender": "男"}
{"image": "3375.png", "category": "16-19", "gender": "男"}
{"image": "3376.png", "category": "16-19", "gender": "男"}
{"image": "3377.png", "category": "20-24", "gender": "男"}
{"image": "3378.png", "category": "16-19", "gender": "男"}
{"image": "3379.png", "category": "16-19", "gender": "男"}
{"image": "338.png", "category": "16-19", "gender": "男"}
{"image": "3380.png", "category": "13-15", "gender": "男"}
{"image": "3381.png", "category": "13-15", "gender": "男"}
{"image": "3382.png", "category": "bug", "gender": null}
{"image": "3383.png", "category": "13-15", "gender": "男"}
{"image": "3384.png", "category": "13-15", "gender": "男"}
{"image": "3385.png", "category": "13-15", "gender": "男"}
{"image": "3386.png", "category": "13-15", "gender": "男"}
{"image": "3387.png", "category": "13-15", "gender": "男"}
{"image": "3388.png", "category": "16-19", "gender": "男"}
{"image": "3389.png", "category": "16-19", "gender": "男"}
{"image": "339.png", "category": "16-19", "gender": "男"}
{"image": "3390.png", "category": "20-24", "gender": "男"}
{"image": "3391.png", "category": "20-24", "gender": "男"}
{"image": "3392.png", "category": "20-24", "gender": "男"}
{"image": "3393.png", "category": "13-15", "gender": "男"}
{"image": "3394.png", "category": "16-19", "gender": "男"}
{"image": "3395.png", "category": "13-15", "gender": "男"}
{"image": "3396.png", "category": "20-24", "gender": "男"}
{"image": "3397.png", "category": "20-24", "gender": "男"}
{"image": "3398.png", "category": "16-19", "gender": "男"}
{"image": "3399.png", "category": "13-15", "gender": "男"}
{"image": "34.png", "category": "16-19", "gender": "男"}
{"image": "340.png", "category": "13-15", "gender": "男"}
{"image": "3400.png", "category": "13-15", "gender": "男"}
{"image": "3401.png", "category": "20-24", "gender": "男"}
{"image": "3402.png", "category": "16-19", "gender": "男"}
{"image": "3403.png", "category": "13-15", "gender": "男"}
{"image": "3404.png", "category": "16-19", "gender": "男"}
{"image": "3405.png", "category": "16-19", "gender": "男"}
{"image": "3406.png", "category": "25-30", "gender": "男"}
{"image": "3407.png", "category": "25-30", "gender": "男"}
{"image": "3408.png", "category": "16-19", "gender": "男"}
{"image": "3409.png", "category": "16-19", "gender": "男"}
{"image": "341.png", "category": "16-19", "gender": "男"}
{"image": "3410.png", "category": "20-24", "gender": "男"}
{"image": "3411.png", "category": "13-15", "gender": "男"}
{"image": "3412.png", "category": "13-15", "gender": "男"}
{"image": "3413.png", "category": "11-12", "gender": "男"}
{"image": "3414.png", "category": "13-15", "gender": "男"}
{"image": "3415.png", "category": "13-15", "gender": "男"}
{"image": "3416.png", "category": "16-19", "gender": "男"}
{"image": "3417.png", "category": "16-19", "gender": "男"}
{"image": "3418.png", "category": "16-19", "gender": "男"}
{"image": "3419.png", "category": "16-19", "gender": "男"}
{"image": "342.png", "category": "16-19", "gender": "男"}
{"image": "3420.png", "category": "20-24", "gender": "男"}
{"image": "3421.png", "category": "20-24", "gender": "男"}
{"image": "3422.png", "category": "20-24", "gender": "男"}
{"image": "3423.png", "category": "25-30", "gender": "男"}
{"image": "3424.png", "category": "20-24", "gender": "男"}
{"image": "3425.png", "category": "16-19", "gender": "男"}
{"image": "3426.png", "category": "16-19", "gender": "男"}
{"image": "3427.png", "category": "16-19", "gender": "男"}
{"image": "3428.png", "category": "16-19", "gender": "男"}
{"image": "3429.png", "category": "20-24", "gender": "男"}
{"image": "343.png", "category": "16-19", "gender": "男"}
{"image": "3430.png", "category": "16-19", "gender": "男"}
{"image": "3431.png", "category": "21-23", "gender": "女"}
{"image": "3432.png", "category": "20-24", "gender": "男"}
{"image": "3433.png", "category": "20-24", "gender": "男"}
{"image": "3434.png", "category": "20-24", "gender": "男"}
{"image": "3435.png", "category": "16-19", "gender": "男"}
{"image": "3436.png", "category": "13-15", "gender": "男"}
{"image": "3437.png", "category": "13-15", "gender": "男"}
{"image": "3438.png", "category": "13-15", "gender": "男"}
{"image": "3439.png", "category": "13-15", "gender": "男"}
{"image": "344.png", "category": "25-30", "gender": "男"}
{"image": "3440.png", "category": "13-15", "gender": "男"}
{"image": "3441.png", "category": "13-15", "gender": "男"}
{"image": "3442.png", "category": "13-15", "gender": "男"}
{"image": "3443.png", "category": "13-15", "gender": "男"}
{"image": "3444.png", "category": "13-15", "gender": "男"}
{"image": "3445.png", "category": "16-19", "gender": "男"}
{"image": "3446.png", "category": "16-19", "gender": "男"}
{"image": "3447.png", "category": "16-19", "gender": "男"}
{"image": "3448.png", "category": "16-19", "gender": "男"}
{"image": "3449.png", "category": "16-19", "gender": "男"}
{"image": "345.png", "category": "20-24", "gender": "男"}
{"image": "3450.png", "category": "20-24", "gender": "男"}
{"image": "3451.png", "category": "16-19", "gender": "男"}
{"image": "3452.png", "category": "20-24", "gender": "男"}
{"image": "3453.png", "category": "13-15", "gender": "男"}
{"image": "3454.png", "category": "16-19", "gender": "男"}
{"image": "3455.png", "category": "16-19", "gender": "男"}
{"image": "3456.png", "category": "16-19", "gender": "男"}
{"image": "3457.png", "category": "16-19", "gender": "男"}
{"image": "3458.png", "category": "16-19", "gender": "男"}
{"image": "3459.png", "category": "13-15", "gender": "男"}
{"image": "346.png", "category": "20-24", "gender": "男"}
{"image": "3460.png", "category": "13-15", "gender": "男"}
{"image": "3461.png", "category": "16-19", "gender": "男"}
{"image": "3462.png", "category": "16-19", "gender": "男"}
{"image": "3463.png", "category": "16-19", "gender": "男"}
{"image": "3464.png", "category": "16-19", "gender": "男"}
{"image": "3465.png", "category": "20-24", "gender": "男"}
{"image": "3466.png", "category": "16-19", "gender": "男"}
{"image": "3467.png", "category": "16-19", "gender": "男"}
{"image": "3468.png", "category": "20-24", "gender": "男"}
{"image": "3469.png", "category": "20-24", "gender": "男"}
{"image": "347.png", "category": "20-24", "gender": "男"}
{"image": "3470.png", "category": "20-24", "gender": "男"}
{"image": "3471.png", "category": "16-19", "gender": "男"}
{"image": "3472.png", "category": "20-24", "gender": "男"}
{"image": "3473.png", "category": "16-19", "gender": "男"}
{"image": "3474.png", "category": "16-19", "gender": "男"}
{"image": "3475.png", "category": "13-15", "gender": "男"}
{"image": "3476.png", "category": "16-19", "gender": "男"}
{"image": "3477.png", "category": "16-19", "gender": "男"}
{"image": "3478.png", "category": "13-15", "gender": "男"}
{"image": "3479.png", "category": "16-19", "gender": "男"}
{"image": "348.png", "category": "20-24", "gender": "男"}
{"image": "3480.png", "category": "16-19", "gender": "男"}
{"image": "3481.png", "category": "16-19", "gender": "男"}
{"image": "3482.png", "category": "20-24", "gender": "男"}
{"image": "3483.png", "category": "20-24", "gender": "男"}
{"image": "3484.png", "category": "16-19", "gender": "男"}
{"image": "3485.png", "category": "13-15", "gender": "男"}
{"image": "3486.png", "category": "16-19", "gender": "男"}
{"image": "3487.png", "category": "16-19", "gender": "男"}
{"image": "3488.png", "category": "16-19", "gender": "男"}
{"image": "3489.png", "category": "16-19", "gender": "男"}
{"image": "349.png", "category": "20-24", "gender": "男"}
{"image": "3490.png", "category": "16-19", "gender": "男"}
{"image": "3491.png", "category": "16-19", "gender": "男"}
{"image": "3492.png", "category": "16-19", "gender": "男"}
{"image": "3493.png", "category": "16-19", "gender": "男"}
{"image": "3494.png", "category": "13-15", "gender": "男"}
{"image": "3495.png", "category": "13-15", "gender": "男"}
{"image": "3496.png", "category": "16-19", "gender": "男"}
{"image": "3497.png", "category": "16-19", "gender": "男"}
{"image": "3498.png", "category": "13-15", "gender": "男"}
{"image": "3499.png", "category": "13-15", "gender": "男"}
{"image": "35.png", "category": "16-19", "gender": "男"}
{"image": "350.png", "category": "16-19", "gender": "男"}
{"image": "3500.png", "category": "20-24", "gender": "男"}
{"image": "3501.png", "category": "20-24", "gender": "男"}
{"image": "3502.png", "category": "16-19", "gender": "男"}
{"image": "3503.png", "category": "16-19", "gender": "男"}
{"image": "3504.png", "category": "20-24", "gender": "男"}
{"image": "3505.png", "category": "20-24", "gender": "男"}
{"image": "3506.png", "category": "20-24", "gender": "男"}
{"image": "3507.png", "category": "16-19", "gender": "男"}
{"image": "3508.png", "category": "20-24", "gender": "男"}
{"image": "3509.png", "category": "16-19", "gender": "男"}
{"image": "351.png", "category": "16-19", "gender": "男"}
{"image": "3510.png", "category": "16-19", "gender": "男"}
{"image": "3511.png", "category": "16-19", "gender": "男"}
{"image": "3512.png", "category": "16-19", "gender": "男"}
{"image": "3513.png", "category": "13-15", "gender": "男"}
{"image": "3514.png", "category": "16-19", "gender": "男"}
{"image": "3515.png", "category": "13-15", "gender": "男"}
{"image": "3516.png", "category": "16-19", "gender": "男"}
{"image": "3517.png", "category": "13-15", "gender": "男"}
{"image": "3518.png", "category": "13-15", "gender": "男"}
{"image": "3519.png", "category": "16-19", "gender": "男"}
{"image": "352.png", "category": "20-24", "gender": "男"}
{"image": "3520.png", "category": "20-24", "gender": "男"}
{"image": "3521.png", "category": "16-19", "gender": "男"}
{"image": "3522.png", "category": "25-30", "gender": "男"}
{"image": "3523.png", "category": "25-30", "gender": "男"}
{"image": "3524.png", "category": "20-24", "gender": "男"}
{"image": "3525.png", "category": "20-24", "gender": "男"}
{"image": "3526.png", "category": "20-24", "gender": "男"}
{"image": "3527.png", "category": "16-19", "gender": "男"}
{"image": "3528.png", "category": "16-19", "gender": "男"}
{"image": "3529.png", "category": "16-19", "gender": "男"}
{"image": "353.png", "category": "20-24", "gender": "男"}
{"image": "3530.png", "category": "16-19", "gender": "男"}
{"image": "3531.png", "category": "16-19", "gender": "男"}
{"image": "3532.png", "category": "16-19", "gender": "男"}
{"image": "3533.png", "category": "16-19", "gender": "男"}
{"image": "3534.png", "category": "16-19", "gender": "男"}
{"image": "3535.png", "category": "13-15", "gender": "男"}
{"image": "3536.png", "category": "13-15", "gender": "男"}
{"image": "3537.png", "category": "13-15", "gender": "男"}
{"image": "3538.png", "category": "16-19", "gender": "男"}
{"image": "3539.png", "category": "bug", "gender": null}
{"image": "354.png", "category": "13-15", "gender": "男"}
{"image": "3540.png", "category": "16-19", "gender": "男"}
{"image": "3541.png", "category": "20-24", "gender": "男"}
{"image": "3542.png", "category": "16-19", "gender": "男"}
{"image": "3543.png", "category": "20-24", "gender": "男"}
{"image": "3544.png", "category": "16-19", "gender": "男"}
{"image": "3545.png", "category": "16-19", "gender": "男"}
{"image": "3546.png", "category": "13-15", "gender": "男"}
{"image": "3547.png", "category": "16-19", "gender": "男"}
{"image": "3548.png", "category": "16-19", "gender": "男"}
{"image": "3549.png", "category": "16-19", "gender": "男"}
{"image": "355.png", "category": "13-15", "gender": "男"}
{"image": "3550.png", "category": "16-19", "gender": "男"}
{"image": "3551.png", "category": "16-19", "gender": "男"}
{"image": "3552.png", "category": "13-15", "gender": "男"}
{"image": "3553.png", "category": "13-15", "gender": "男"}
{"image": "3554.png", "category": "13-15", "gender": "男"}
{"image": "3555.png", "category": "13-15", "gender": "男"}
{"image": "3556.png", "category": "20-24", "gender": "男"}
{"image": "3557.png", "category": "20-24", "gender": "男"}
{"image": "3558.png", "category": "20-24", "gender": "男"}
{"image": "3559.png", "category": "20-24", "gender": "男"}
{"image": "356.png", "category": "20-24", "gender": "男"}
{"image": "3560.png", "category": "20-24", "gender": "男"}
{"image": "3561.png", "category": "20-24", "gender": "男"}
{"image": "3562.png", "category": "25-30", "gender": "男"}
{"image": "3563.png", "category": "13-15", "gender": "男"}
{"image": "3564.png", "category": "13-15", "gender": "男"}
{"image": "3565.png", "category": "bug", "gender": null}
{"image": "3566.png", "category": "20-24", "gender": "男"}
{"image": "3567.png", "category": "bug", "gender": null}
{"image": "3568.png", "category": "bug", "gender": null}
{"image": "3569.png", "category": "20-24", "gender": "男"}
{"image": "357.png", "category": "16-19", "gender": "男"}
{"image": "3570.png", "category": "16-19", "gender": "男"}
{"image": "3571.png", "category": "20-24", "gender": "男"}
{"image": "3572.png", "category": "16-19", "gender": "男"}
{"image": "3573.png", "category": "20-24", "gender": "男"}
{"image": "3574.png", "category": "11-12", "gender": "男"}
{"image": "3575.png", "category": "13-15", "gender": "男"}
{"image": "3576.png", "category": "13-15", "gender": "男"}
{"image": "3577.png", "category": "13-15", "gender": "男"}
{"image": "3578.png", "category": "13-15", "gender": "男"}
{"image": "3579.png", "category": "13-15", "gender": "男"}
{"image": "358.png", "category": "16-19", "gender": "男"}
{"image": "3580.png", "category": "24-26", "gender": "女"}
{"image": "3581.png", "category": "16-19", "gender": "男"}
{"image": "3582.png", "category": "16-19", "gender": "男"}
{"image": "3583.png", "category": "16-19", "gender": "男"}
{"image": "3584.png", "category": "13-15", "gender": "男"}
{"image": "3585.png", "category": "13-15", "gender": "男"}
{"image": "3586.png", "category": "20-24", "gender": "男"}
{"image": "3587.png", "category": "20-24", "gender": "男"}
{"image": "3588.png", "category": "20-24", "gender": "男"}
{"image": "3589.png", "category": "16-19", "gender": "男"}
{"image": "359.png", "category": "20-24", "gender": "男"}
{"image": "3590.png", "category": "16-19", "gender": "男"}
{"image": "3591.png", "category": "16-19", "gender": "男"}
{"image": "3592.png", "category": "16-19", "gender": "男"}
{"image": "3593.png", "category": "16-19", "gender": "男"}
{"image": "3594.png", "category": "16-19", "gender": "男"}
{"image": "3595.png", "category": "16-19", "gender": "男"}
{"image": "3596.png", "category": "20-24", "gender": "男"}
{"image": "3597.png", "category": "20-24", "gender": "男"}
{"image": "3598.png", "category": "20-24", "gender": "男"}
{"image": "3599.png", "category": "20-24", "gender": "男"}
{"image": "36.png", "category": "16-19", "gender": "男"}
{"image": "360.png", "category": "16-19", "gender": "男"}
{"image": "3600.png", "category": "16-19", "gender": "男"}
{"image": "3601.png", "category": "16-19", "gender": "男"}
{"image": "3602.png", "category": "16-19", "gender": "男"}
{"image": "3603.png", "category": "16-19", "gender": "男"}
{"image": "3604.png", "category": "16-19", "gender": "男"}
{"image": "3605.png", "category": "16-19", "gender": "男"}
{"image": "3606.png", "category": "13-15", "gender": "男"}
{"image": "3607.png", "category": "13-15", "gender": "男"}
{"image": "3608.png", "category": "20-24", "gender": "男"}
{"image": "3609.png", "category": "20-24", "gender": "男"}
{"image": "361.png", "category": "16-19", "gender": "男"}
{"image": "3610.png", "category": "20-24", "gender": "男"}
{"image": "3611.png", "category": "25-30", "gender": "男"}
{"image": "3612.png", "category": "25-30", "gender": "男"}
{"image": "3613.png", "category": "25-30", "gender": "男"}
{"image": "3614.png", "category": "25-30", "gender": "男"}
{"image": "3615.png", "category": "25-30", "gender": "男"}
{"image": "3616.png", "category": "20-24", "gender": "男"}
{"image": "3617.png", "category": "16-19", "gender": "男"}
{"image": "3618.png", "category": "16-19", "gender": "男"}
{"image": "3619.png", "category": "16-19", "gender": "男"}
{"image": "362.png", "category": "16-19", "gender": "男"}
{"image": "3620.png", "category": "16-19", "gender": "男"}
{"image": "3621.png", "category": "16-19", "gender": "男"}
{"image": "3622.png", "category": "16-19", "gender": "男"}
{"image": "3623.png", "category": "bug", "gender": null}
{"image": "3624.png", "category": "25-30", "gender": "男"}
{"image": "3625.png", "category": "20-24", "gender": "男"}
{"image": "3626.png", "category": "25-30", "gender": "男"}
{"image": "3627.png", "category": "25-30", "gender": "男"}
{"image": "3628.png", "category": "bug", "gender": null}
{"image": "3629.png", "category": "25-30", "gender": "男"}
{"image": "363.png", "category": "13-15", "gender": "男"}
{"image": "3630.png", "category": "20-24", "gender": "男"}
{"image": "3631.png", "category": "25-30", "gender": "男"}
{"image": "3632.png", "category": "20-24", "gender": "男"}
{"image": "3633.png", "category": "20-24", "gender": "男"}
{"image": "3634.png", "category": "20-24", "gender": "男"}
{"image": "3635.png", "category": "16-19", "gender": "男"}
{"image": "3636.png", "category": "16-19", "gender": "男"}
{"image": "3637.png", "category": "16-19", "gender": "男"}
{"image": "3638.png", "category": "16-19", "gender": "男"}
{"image": "3639.png", "category": "16-19", "gender": "男"}
{"image": "364.png", "category": "16-19", "gender": "男"}
{"image": "3640.png", "category": "16-19", "gender": "男"}
{"image": "3641.png", "category": "16-19", "gender": "男"}
{"image": "3642.png", "category": "16-19", "gender": "男"}
{"image": "3643.png", "category": "13-15", "gender": "男"}
{"image": "3644.png", "category": "13-15", "gender": "男"}
{"image": "3645.png", "category": "13-15", "gender": "男"}
{"image": "3646.png", "category": "13-15", "gender": "男"}
{"image": "3647.png", "category": "13-15", "gender": "男"}
{"image": "3648.png", "category": "13-15", "gender": "男"}
{"image": "3649.png", "category": "13-15", "gender": "男"}
{"image": "365.png", "category": "16-19", "gender": "男"}
{"image": "3650.png", "category": "16-19", "gender": "男"}
{"image": "3651.png", "category": "16-19", "gender": "男"}
{"image": "3652.png", "category": "13-15", "gender": "男"}
{"image": "3653.png", "category": "20-24", "gender": "男"}
{"image": "3654.png", "category": "16-19", "gender": "男"}
{"image": "3655.png", "category": "16-19", "gender": "男"}
{"image": "3656.png", "category": "16-19", "gender": "男"}
{"image": "3657.png", "category": "20-24", "gender": "男"}
{"image": "3658.png", "category": "16-19", "gender": "男"}
{"image": "3659.png", "category": "16-19", "gender": "男"}
{"image": "366.png", "category": "16-19", "gender": "男"}
{"image": "3660.png", "category": "16-19", "gender": "男"}
{"image": "3661.png", "category": "16-19", "gender": "男"}
{"image": "3662.png", "category": "16-19", "gender": "男"}
{"image": "3663.png", "category": "13-15", "gender": "男"}
{"image": "3664.png", "category": "16-19", "gender": "男"}
{"image": "3665.png", "category": "16-19", "gender": "男"}
{"image": "3666.png", "category": "16-19", "gender": "男"}
{"image": "3667.png", "category": "13-15", "gender": "男"}
{"image": "3668.png", "category": "13-15", "gender": "男"}
{"image": "3669.png", "category": "16-19", "gender": "男"}
{"image": "367.png", "category": "16-19", "gender": "男"}
{"image": "3670.png", "category": "16-19", "gender": "男"}
{"image": "3671.png", "category": "16-19", "gender": "男"}
{"image": "3672.png", "category": "16-19", "gender": "男"}
{"image": "3673.png", "category": "16-19", "gender": "男"}
{"image": "3674.png", "category": "16-19", "gender": "男"}
{"image": "3675.png", "category": "16-19", "gender": "男"}
{"image": "3676.png", "category": "16-19", "gender": "男"}
{"image": "3677.png", "category": "16-19", "gender": "男"}
{"image": "3678.png", "category": "16-19", "gender": "男"}
{"image": "3679.png", "category": "16-19", "gender": "男"}
{"image": "368.png", "category": "16-19", "gender": "男"}
{"image": "3680.png", "category": "16-19", "gender": "男"}
{"image": "3681.png", "category": "16-19", "gender": "男"}
{"image": "3682.png", "category": "16-19", "gender": "男"}
{"image": "3683.png", "category": "16-19", "gender": "男"}
{"image": "3684.png", "category": "20-24", "gender": "男"}
{"image": "3685.png", "category": "16-19", "gender": "男"}
{"image": "3686.png", "category": "16-19", "gender": "男"}
{"image": "3687.png", "category": "16-19", "gender": "男"}
{"image": "3688.png", "category": "16-19", "gender": "男"}
{"image": "3689.png", "category": "16-19", "gender": "男"}
{"image": "369.png", "category": "16-19", "gender": "男"}
{"image": "3690.png", "category": "16-19", "gender": "男"}
{"image": "3691.png", "category": "20-24", "gender": "男"}
{"image": "3692.png", "category": "20-24", "gender": "男"}
{"image": "3693.png", "category": "20-24", "gender": "男"}
{"image": "3694.png", "category": "16-19", "gender": "男"}
{"image": "3695.png", "category": "16-19", "gender": "男"}
{"image": "3696.png", "category": "16-19", "gender": "男"}
{"image": "3697.png", "category": "16-19", "gender": "男"}
{"image": "3698.png", "category": "20-24", "gender": "男"}
{"image": "3699.png", "category": "20-24", "gender": "男"}
{"image": "37.png", "category": "20-24", "gender": "男"}
{"image": "370.png", "category": "16-19", "gender": "男"}
{"image": "3700.png", "category": "20-24", "gender": "男"}
{"image": "3701.png", "category": "20-24", "gender": "男"}
{"image": "3702.png", "category": "16-19", "gender": "男"}
{"image": "3703.png", "category": "16-19", "gender": "男"}
{"image": "3704.png", "category": "13-15", "gender": "男"}
{"image": "3705.png", "category": "13-15", "gender": "男"}
{"image": "3706.png", "category": "16-19", "gender": "男"}
{"image": "3707.png", "category": "13-15", "gender": "男"}
{"image": "3708.png", "category": "16-19", "gender": "男"}
{"image": "3709.png", "category": "16-19", "gender": "男"}
{"image": "371.png", "category": "16-19", "gender": "男"}
{"image": "3710.png", "category": "13-15", "gender": "男"}
{"image": "3711.png", "category": "13-15", "gender": "男"}
{"image": "3712.png", "category": "13-15", "gender": "男"}
{"image": "3713.png", "category": "13-15", "gender": "男"}
{"image": "3714.png", "category": "16-19", "gender": "男"}
{"image": "3715.png", "category": "16-19", "gender": "男"}
{"image": "3716.png", "category": "16-19", "gender": "男"}
{"image": "3717.png", "category": "20-24", "gender": "男"}
{"image": "3718.png", "category": "25-30", "gender": "男"}
{"image": "3719.png", "category": "16-19", "gender": "男"}
{"image": "372.png", "category": "16-19", "gender": "男"}
{"image": "3720.png", "category": "16-19", "gender": "男"}
{"image": "3721.png", "category": "13-15", "gender": "男"}
{"image": "3722.png", "category": "16-19", "gender": "男"}
{"image": "3723.png", "category": "16-19", "gender": "男"}
{"image": "3724.png", "category": "13-15", "gender": "男"}
{"image": "3725.png", "category": "16-19", "gender": "男"}
{"image": "3726.png", "category": "16-19", "gender": "男"}
{"image": "3727.png", "category": "16-19", "gender": "男"}
{"image": "3728.png", "category": "16-19", "gender": "男"}
{"image": "3729.png", "category": "16-19", "gender": "男"}
{"image": "373.png", "category": "16-19", "gender": "男"}
{"image": "3730.png", "category": "16-19", "gender": "男"}
{"image": "3731.png", "category": "16-19", "gender": "男"}
{"image": "3732.png", "category": "16-19", "gender": "男"}
{"image": "3733.png", "category": "16-19", "gender": "男"}
{"image": "3734.png", "category": "13-15", "gender": "男"}
{"image": "3735.png", "category": "13-15", "gender": "男"}
{"image": "3736.png", "category": "13-15", "gender": "男"}
{"image": "3737.png", "category": "20-24", "gender": "男"}
{"image": "3738.png", "category": "16-19", "gender": "男"}
{"image": "3739.png", "category": "20-24", "gender": "男"}
{"image": "374.png", "category": "16-19", "gender": "男"}
{"image": "3740.png", "category": "16-19", "gender": "男"}
{"image": "3741.png", "category": "16-19", "gender": "男"}
{"image": "3742.png", "category": "16-19", "gender": "男"}
{"image": "3743.png", "category": "20-24", "gender": "男"}
{"image": "3744.png", "category": "16-19", "gender": "男"}
{"image": "3745.png", "category": "16-19", "gender": "男"}
{"image": "3746.png", "category": "13-15", "gender": "男"}
{"image": "3747.png", "category": "16-19", "gender": "男"}
{"image": "3748.png", "category": "16-19", "gender": "男"}
{"image": "3749.png", "category": "16-19", "gender": "男"}
{"image": "375.png", "category": "16-19", "gender": "男"}
{"image": "3750.png", "category": "13-15", "gender": "男"}
{"image": "3751.png", "category": "13-15", "gender": "男"}
{"image": "3752.png", "category": "16-19", "gender": "男"}
{"image": "3753.png", "category": "20-24", "gender": "男"}
{"image": "3754.png", "category": "20-24", "gender": "男"}
{"image": "3755.png", "category": "16-19", "gender": "男"}
{"image": "3756.png", "category": "16-19", "gender": "男"}
{"image": "3757.png", "category": "16-19", "gender": "男"}
{"image": "3758.png", "category": "16-19", "gender": "男"}
{"image": "3759.png", "category": "16-19", "gender": "男"}
{"image": "376.png", "category": "13-15", "gender": "男"}
{"image": "3760.png", "category": "16-19", "gender": "男"}
{"image": "3761.png", "category": "16-19", "gender": "男"}
{"image": "3762.png", "category": "16-19", "gender": "男"}
{"image": "3763.png", "category": "13-15", "gender": "男"}
{"image": "3764.png", "category": "13-15", "gender": "男"}
{"image": "3765.png", "category": "13-15", "gender": "男"}
{"image": "3766.png", "category": "13-15", "gender": "男"}
{"image": "3767.png", "category": "13-15", "gender": "男"}
{"image": "3768.png", "category": "16-19", "gender": "男"}
{"image": "3769.png", "category": "16-19", "gender": "男"}
{"image": "377.png", "category": "16-19", "gender": "男"}
{"image": "3770.png", "category": "16-19", "gender": "男"}
{"image": "3771.png", "category": "20-24", "gender": "男"}
{"image": "3772.png", "category": "20-24", "gender": "男"}
{"image": "3773.png", "category": "20-24", "gender": "男"}
{"image": "3774.png", "category": "13-15", "gender": "男"}
{"image": "3775.png", "category": "13-15", "gender": "男"}
{"image": "3776.png", "category": "13-15", "gender": "男"}
{"image": "3777.png", "category": "13-15", "gender": "男"}
{"image": "3778.png", "category": "13-15", "gender": "男"}
{"image": "3779.png", "category": "13-15", "gender": "男"}
{"image": "378.png", "category": "13-15", "gender": "男"}
{"image": "3780.png", "category": "13-15", "gender": "男"}
{"image": "3781.png", "category": "13-15", "gender": "男"}
{"image": "3782.png", "category": "13-15", "gender": "男"}
{"image": "3783.png", "category": "13-15", "gender": "男"}
{"image": "3784.png", "category": "16-19", "gender": "男"}
{"image": "3785.png", "category": "16-19", "gender": "男"}
{"image": "3786.png", "category": "16-19", "gender": "男"}
{"image": "3787.png", "category": "13-15", "gender": "男"}
{"image": "3788.png", "category": "13-15", "gender": "男"}
{"image": "3789.png", "category": "16-19", "gender": "男"}
{"image": "379.png", "category": "16-19", "gender": "男"}
{"image": "3790.png", "category": "16-19", "gender": "男"}
{"image": "3791.png", "category": "20-24", "gender": "男"}
{"image": "3792.png", "category": "16-19", "gender": "男"}
{"image": "3793.png", "category": "20-24", "gender": "男"}
{"image": "3794.png", "category": "16-19", "gender": "男"}
{"image": "3795.png", "category": "16-19", "gender": "男"}
{"image": "3796.png", "category": "16-19", "gender": "男"}
{"image": "3797.png", "category": "bug", "gender": null}
{"image": "3798.png", "category": "13-15", "gender": "男"}
{"image": "3799.png", "category": "20-24", "gender": "男"}
{"image": "38.png", "category": "20-24", "gender": "男"}
{"image": "380.png", "category": "16-19", "gender": "男"}
{"image": "3800.png", "category": "13-15", "gender": "男"}
{"image": "3801.png", "category": "13-15", "gender": "男"}
{"image": "3802.png", "category": "20-24", "gender": "男"}
{"image": "3803.png", "category": "20-24", "gender": "男"}
{"image": "3804.png", "category": "16-19", "gender": "男"}
{"image": "3805.png", "category": "20-24", "gender": "男"}
{"image": "3806.png", "category": "20-24", "gender": "男"}
{"image": "3807.png", "category": "16-19", "gender": "男"}
{"image": "3808.png", "category": "16-19", "gender": "男"}
{"image": "3809.png", "category": "16-19", "gender": "男"}
{"image": "381.png", "category": "20-24", "gender": "男"}
{"image": "3810.png", "category": "16-19", "gender": "男"}
{"image": "3811.png", "category": "16-19", "gender": "男"}
{"image": "3812.png", "category": "16-19", "gender": "男"}
{"image": "3813.png", "category": "16-19", "gender": "男"}
{"image": "3814.png", "category": "16-19", "gender": "男"}
{"image": "3815.png", "category": "16-19", "gender": "男"}
{"image": "3816.png", "category": "13-15", "gender": "男"}
{"image": "3817.png", "category": "20-24", "gender": "男"}
{"image": "3818.png", "category": "16-19", "gender": "男"}
{"image": "3819.png", "category": "20-24", "gender": "男"}
{"image": "382.png", "category": "16-19", "gender": "男"}
{"image": "3820.png", "category": "25-30", "gender": "男"}
{"image": "3821.png", "category": "35-40", "gender": "男"}
{"image": "3822.png", "category": "16-19", "gender": "男"}
{"image": "3823.png", "category": "16-19", "gender": "男"}
{"image": "3824.png", "category": "16-19", "gender": "男"}
{"image": "3825.png", "category": "16-19", "gender": "男"}
{"image": "3826.png", "category": "16-19", "gender": "男"}
{"image": "3827.png", "category": "16-19", "gender": "男"}
{"image": "3828.png", "category": "16-19", "gender": "男"}
{"image": "3829.png", "category": "16-19", "gender": "男"}
{"image": "383.png", "category": "16-19", "gender": "男"}
{"image": "3830.png", "category": "16-19", "gender": "男"}
{"image": "3831.png", "category": "bug", "gender": null}
{"image": "3832.png", "category": "13-15", "gender": "男"}
{"image": "3833.png", "category": "13-15", "gender": "男"}
{"image": "3834.png", "category": "20-24", "gender": "男"}
{"image": "3835.png", "category": "16-19", "gender": "男"}
{"image": "3836.png", "category": "20-24", "gender": "男"}
{"image": "3837.png", "category": "16-19", "gender": "男"}
{"image": "3838.png", "category": "16-19", "gender": "男"}
{"image": "3839.png", "category": "16-19", "gender": "男"}
{"image": "384.png", "category": "13-15", "gender": "男"}
{"image": "3840.png", "category": "16-19", "gender": "男"}
{"image": "3841.png", "category": "16-19", "gender": "男"}
{"image": "3842.png", "category": "16-19", "gender": "男"}
{"image": "3843.png", "category": "13-15", "gender": "男"}
{"image": "3844.png", "category": "13-15", "gender": "男"}
{"image": "3845.png", "category": "13-15", "gender": "男"}
{"image": "3846.png", "category": "13-15", "gender": "男"}
{"image": "3847.png", "category": "20-24", "gender": "男"}
{"image": "3848.png", "category": "16-19", "gender": "男"}
{"image": "3849.png", "category": "16-19", "gender": "男"}
{"image": "385.png", "category": "13-15", "gender": "男"}
{"image": "3850.png", "category": "16-19", "gender": "男"}
{"image": "3851.png", "category": "16-19", "gender": "男"}
{"image": "3852.png", "category": "16-19", "gender": "男"}
{"image": "3853.png", "category": "16-19", "gender": "男"}
{"image": "3854.png", "category": "13-15", "gender": "男"}
{"image": "3855.png", "category": "13-15", "gender": "男"}
{"image": "3856.png", "category": "13-15", "gender": "男"}
{"image": "3857.png", "category": "20-24", "gender": "男"}
{"image": "3858.png", "category": "16-19", "gender": "男"}
{"image": "3859.png", "category": "16-19", "gender": "男"}
{"image": "386.png", "category": "16-19", "gender": "男"}
{"image": "3860.png", "category": "16-19", "gender": "男"}
{"image": "3861.png", "category": "16-19", "gender": "男"}
{"image": "3862.png", "category": "13-15", "gender": "男"}
{"image": "3863.png", "category": "13-15", "gender": "男"}
{"image": "3864.png", "category": "20-24", "gender": "男"}
{"image": "3865.png", "category": "13-15", "gender": "男"}
{"image": "3866.png", "category": "16-19", "gender": "男"}
{"image": "3867.png", "category": "13-15", "gender": "男"}
{"image": "3868.png", "category": "16-19", "gender": "男"}
{"image": "3869.png", "category": "13-15", "gender": "男"}
{"image": "387.png", "category": "16-19", "gender": "男"}
{"image": "3870.png", "category": "16-19", "gender": "男"}
{"image": "3871.png", "category": "20-24", "gender": "男"}
{"image": "3872.png", "category": "16-19", "gender": "男"}
{"image": "3873.png", "category": "16-19", "gender": "男"}
{"image": "3874.png", "category": "16-19", "gender": "男"}
{"image": "3875.png", "category": "16-19", "gender": "男"}
{"image": "3876.png", "category": "13-15", "gender": "男"}
{"image": "3877.png", "category": "16-19", "gender": "男"}
{"image": "3878.png", "category": "16-19", "gender": "男"}
{"image": "3879.png", "category": "16-19", "gender": "男"}
{"image": "388.png", "category": "16-19", "gender": "男"}
{"image": "3880.png", "category": "16-19", "gender": "男"}
{"image": "3881.png", "category": "16-19", "gender": "男"}
{"image": "3882.png", "category": "16-19", "gender": "男"}
{"image": "3883.png", "category": "20-24", "gender": "男"}
{"image": "3884.png", "category": "20-24", "gender": "男"}
{"image": "3885.png", "category": "16-19", "gender": "男"}
{"image": "3886.png", "category": "16-19", "gender": "男"}
{"image": "3887.png", "category": "13-15", "gender": "男"}
{"image": "3888.png", "category": "16-19", "gender": "男"}
{"image": "3889.png", "category": "20-24", "gender": "男"}
{"image": "389.png", "category": "25-30", "gender": "男"}
{"image": "3890.png", "category": "20-24", "gender": "男"}
{"image": "3891.png", "category": "16-19", "gender": "男"}
{"image": "3892.png", "category": "bug", "gender": null}
{"image": "3893.png", "category": "bug", "gender": null}
{"image": "3894.png", "category": "20-24", "gender": "男"}
{"image": "3895.png", "category": "16-19", "gender": "男"}
{"image": "3896.png", "category": "16-19", "gender": "男"}
{"image": "3897.png", "category": "13-15", "gender": "男"}
{"image": "3898.png", "category": "16-19", "gender": "男"}
{"image": "3899.png", "category": "16-19", "gender": "男"}
{"image": "39.png", "category": "16-19", "gender": "男"}
{"image": "390.png", "category": "16-19", "gender": "男"}
{"image": "3900.png", "category": "13-15", "gender": "男"}
{"image": "3901.png", "category": "13-15", "gender": "男"}
{"image": "3902.png", "category": "16-19", "gender": "男"}
{"image": "3903.png", "category": "13-15", "gender": "男"}
{"image": "3904.png", "category": "13-15", "gender": "男"}
{"image": "3905.png", "category": "13-15", "gender": "男"}
{"image": "3906.png", "category": "13-15", "gender": "男"}
{"image": "3907.png", "category": "16-19", "gender": "男"}
{"image": "3908.png", "category": "25-30", "gender": "男"}
{"image": "3909.png", "category": "25-30", "gender": "男"}
{"image": "391.png", "category": "16-19", "gender": "男"}
{"image": "3910.png", "category": "25-30", "gender": "男"}
{"image": "3911.png", "category": "20-24", "gender": "男"}
{"image": "3912.png", "category": "20-24", "gender": "男"}
{"image": "3913.png", "category": "13-15", "gender": "男"}
{"image": "3914.png", "category": "13-15", "gender": "男"}
{"image": "3915.png", "category": "16-19", "gender": "男"}
{"image": "3916.png", "category": "16-19", "gender": "男"}
{"image": "3917.png", "category": "16-19", "gender": "男"}
{"image": "3918.png", "category": "16-19", "gender": "男"}
{"image": "3919.png", "category": "13-15", "gender": "男"}
{"image": "392.png", "category": "16-19", "gender": "男"}
{"image": "3920.png", "category": "16-19", "gender": "男"}
{"image": "3921.png", "category": "13-15", "gender": "男"}
{"image": "3922.png", "category": "16-19", "gender": "男"}
{"image": "3923.png", "category": "13-15", "gender": "男"}
{"image": "3924.png", "category": "13-15", "gender": "男"}
{"image": "3925.png", "category": "16-19", "gender": "男"}
{"image": "3926.png", "category": "13-15", "gender": "男"}
{"image": "3927.png", "category": "16-19", "gender": "男"}
{"image": "3928.png", "category": "16-19", "gender": "男"}
{"image": "3929.png", "category": "16-19", "gender": "男"}
{"image": "393.png", "category": "16-19", "gender": "男"}
{"image": "3930.png", "category": "16-19", "gender": "男"}
{"image": "3931.png", "category": "16-19", "gender": "男"}
{"image": "3932.png", "category": "16-19", "gender": "男"}
{"image": "3933.png", "category": "13-15", "gender": "男"}
{"image": "3934.png", "category": "16-19", "gender": "男"}
{"image": "3935.png", "category": "16-19", "gender": "男"}
{"image": "3936.png", "category": "16-19", "gender": "男"}
{"image": "3937.png", "category": "16-19", "gender": "男"}
{"image": "3938.png", "category": "25-30", "gender": "男"}
{"image": "3939.png", "category": "25-30", "gender": "男"}
{"image": "394.png", "category": "25-30", "gender": "男"}
{"image": "3940.png", "category": "25-30", "gender": "男"}
{"image": "3941.png", "category": "25-30", "gender": "男"}
{"image": "3942.png", "category": "13-15", "gender": "男"}
{"image": "3943.png", "category": "20-24", "gender": "男"}
{"image": "3944.png", "category": "20-24", "gender": "男"}
{"image": "3945.png", "category": "16-19", "gender": "男"}
{"image": "3946.png", "category": "16-19", "gender": "男"}
{"image": "3947.png", "category": "16-19", "gender": "男"}
{"image": "3948.png", "category": "bug", "gender": null}
{"image": "3949.png", "category": "16-19", "gender": "男"}
{"image": "395.png", "category": "16-19", "gender": "男"}
{"image": "3950.png", "category": "16-19", "gender": "男"}
{"image": "3951.png", "category": "16-19", "gender": "男"}
{"image": "3952.png", "category": "16-19", "gender": "男"}
{"image": "3953.png", "category": "bug", "gender": null}
{"image": "3954.png", "category": "16-19", "gender": "男"}
{"image": "3955.png", "category": "16-19", "gender": "男"}
{"image": "3956.png", "category": "20-24", "gender": "男"}
{"image": "3957.png", "category": "20-24", "gender": "男"}
{"image": "3958.png", "category": "20-24", "gender": "男"}
{"image": "3959.png", "category": "16-19", "gender": "男"}
{"image": "396.png", "category": "16-19", "gender": "男"}
{"image": "3960.png", "category": "16-19", "gender": "男"}
{"image": "3961.png", "category": "16-19", "gender": "男"}
{"image": "3962.png", "category": "20-24", "gender": "男"}
{"image": "3963.png", "category": "16-19", "gender": "男"}
{"image": "3964.png", "category": "13-15", "gender": "男"}
{"image": "3965.png", "category": "13-15", "gender": "男"}
{"image": "3966.png", "category": "13-15", "gender": "男"}
{"image": "3967.png", "category": "16-19", "gender": "男"}
{"image": "3968.png", "category": "16-19", "gender": "男"}
{"image": "3969.png", "category": "16-19", "gender": "男"}
{"image": "397.png", "category": "16-19", "gender": "男"}
{"image": "3970.png", "category": "16-19", "gender": "男"}
{"image": "3971.png", "category": "20-24", "gender": "男"}
{"image": "3972.png", "category": "20-24", "gender": "男"}
{"image": "3973.png", "category": "20-24", "gender": "男"}
{"image": "3974.png", "category": "20-24", "gender": "男"}
{"image": "3975.png", "category": "20-24", "gender": "男"}
{"image": "3976.png", "category": "13-15", "gender": "男"}
{"image": "3977.png", "category": "16-19", "gender": "男"}
{"image": "3978.png", "category": "13-15", "gender": "男"}
{"image": "3979.png", "category": "16-19", "gender": "男"}
{"image": "398.png", "category": "13-15", "gender": "男"}
{"image": "3980.png", "category": "13-15", "gender": "男"}
{"image": "3981.png", "category": "16-19", "gender": "男"}
{"image": "3982.png", "category": "16-19", "gender": "男"}
{"image": "3983.png", "category": "16-19", "gender": "男"}
{"image": "3984.png", "category": "16-19", "gender": "男"}
{"image": "3985.png", "category": "13-15", "gender": "男"}
{"image": "3986.png", "category": "13-15", "gender": "男"}
{"image": "3987.png", "category": "13-15", "gender": "男"}
{"image": "3988.png", "category": "13-15", "gender": "男"}
{"image": "3989.png", "category": "13-15", "gender": "男"}
{"image": "399.png", "category": "13-15", "gender": "男"}
{"image": "3990.png", "category": "25-30", "gender": "男"}
{"image": "3991.png", "category": "16-19", "gender": "男"}
{"image": "3992.png", "category": "16-19", "gender": "男"}
{"image": "3993.png", "category": "13-15", "gender": "男"}
{"image": "3994.png", "category": "bug", "gender": null}
{"image": "3995.png", "category": "13-15", "gender": "男"}
{"image": "3996.png", "category": "16-19", "gender": "男"}
{"image": "3997.png", "category": "13-15", "gender": "男"}
{"image": "3998.png", "category": "13-15", "gender": "男"}
{"image": "3999.png", "category": "16-19", "gender": "男"}
{"image": "4.png", "category": "20-24", "gender": "男"}
{"image": "40.png", "category": "13-15", "gender": "男"}
{"image": "400.png", "category": "16-19", "gender": "男"}
{"image": "4000.png", "category": "13-15", "gender": "男"}
{"image": "4001.png", "category": "16-19", "gender": "男"}
{"image": "4002.png", "category": "16-19", "gender": "男"}
{"image": "4003.png", "category": "16-19", "gender": "男"}
{"image": "4004.png", "category": "13-15", "gender": "男"}
{"image": "4005.png", "category": "20-24", "gender": "男"}
{"image": "4006.png", "category": "25-30", "gender": "男"}
{"image": "4007.png", "category": "25-30", "gender": "男"}
{"image": "4008.png", "category": "20-24", "gender": "男"}
{"image": "4009.png", "category": "20-24", "gender": "男"}
{"image": "401.png", "category": "16-19", "gender": "男"}
{"image": "4010.png", "category": "16-19", "gender": "男"}
{"image": "4011.png", "category": "16-19", "gender": "男"}
{"image": "4012.png", "category": "16-19", "gender": "男"}
{"image": "4013.png", "category": "16-19", "gender": "男"}
{"image": "4014.png", "category": "20-24", "gender": "男"}
{"image": "4015.png", "category": "16-19", "gender": "男"}
{"image": "4016.png", "category": "13-15", "gender": "男"}
{"image": "4017.png", "category": "13-15", "gender": "男"}
{"image": "4018.png", "category": "20-24", "gender": "男"}
{"image": "4019.png", "category": "16-19", "gender": "男"}
{"image": "402.png", "category": "16-19", "gender": "男"}
{"image": "4020.png", "category": "16-19", "gender": "男"}
{"image": "4021.png", "category": "16-19", "gender": "男"}
{"image": "4022.png", "category": "20-24", "gender": "男"}
{"image": "4023.png", "category": "20-24", "gender": "男"}
{"image": "4024.png", "category": "16-19", "gender": "男"}
{"image": "4025.png", "category": "20-24", "gender": "男"}
{"image": "4026.png", "category": "20-24", "gender": "男"}
{"image": "4027.png", "category": "25-30", "gender": "男"}
{"image": "4028.png", "category": "20-24", "gender": "男"}
{"image": "4029.png", "category": "25-30", "gender": "男"}
{"image": "403.png", "category": "20-24", "gender": "男"}
{"image": "4030.png", "category": "20-24", "gender": "男"}
{"image": "4031.png", "category": "20-24", "gender": "男"}
{"image": "4032.png", "category": "20-24", "gender": "男"}
{"image": "4033.png", "category": "16-19", "gender": "男"}
{"image": "4034.png", "category": "16-19", "gender": "男"}
{"image": "4035.png", "category": "21-23", "gender": "女"}
{"image": "4036.png", "category": "16-19", "gender": "男"}
{"image": "4037.png", "category": "20-24", "gender": "男"}
{"image": "4038.png", "category": "bug", "gender": null}
{"image": "4039.png", "category": "25-30", "gender": "男"}
{"image": "404.png", "category": "20-24", "gender": "男"}
{"image": "4040.png", "category": "16-19", "gender": "男"}
{"image": "4041.png", "category": "16-19", "gender": "男"}
{"image": "4042.png", "category": "13-15", "gender": "男"}
{"image": "4043.png", "category": "13-15", "gender": "男"}
{"image": "4044.png", "category": "13-15", "gender": "男"}
{"image": "4045.png", "category": "13-15", "gender": "男"}
{"image": "4046.png", "category": "13-15", "gender": "男"}
{"image": "4047.png", "category": "13-15", "gender": "男"}
{"image": "4048.png", "category": "13-15", "gender": "男"}
{"image": "4049.png", "category": "13-15", "gender": "男"}
{"image": "405.png", "category": "13-15", "gender": "男"}
{"image": "4050.png", "category": "13-15", "gender": "男"}
{"image": "4051.png", "category": "13-15", "gender": "男"}
{"image": "4052.png", "category": "bug", "gender": null}
{"image": "4053.png", "category": "20-24", "gender": "男"}
{"image": "4054.png", "category": "16-19", "gender": "男"}
{"image": "4055.png", "category": "20-24", "gender": "男"}
{"image": "4056.png", "category": "16-19", "gender": "男"}
{"image": "4057.png", "category": "13-15", "gender": "男"}
{"image": "4058.png", "category": "bug", "gender": null}
{"image": "4059.png", "category": "25-30", "gender": "男"}
{"image": "406.png", "category": "20-24", "gender": "男"}
{"image": "4060.png", "category": "25-30", "gender": "男"}
{"image": "4061.png", "category": "25-30", "gender": "男"}
{"image": "4062.png", "category": "20-24", "gender": "男"}
{"image": "4063.png", "category": "20-24", "gender": "男"}
{"image": "4064.png", "category": "20-24", "gender": "男"}
{"image": "4065.png", "category": "13-15", "gender": "男"}
{"image": "4066.png", "category": "16-19", "gender": "男"}
{"image": "4067.png", "category": "16-19", "gender": "男"}
{"image": "4068.png", "category": "20-24", "gender": "男"}
{"image": "4069.png", "category": "16-19", "gender": "男"}
{"image": "407.png", "category": "20-24", "gender": "男"}
{"image": "4070.png", "category": "16-19", "gender": "男"}
{"image": "4071.png", "category": "16-19", "gender": "男"}
{"image": "4072.png", "category": "20-24", "gender": "男"}
{"image": "4073.png", "category": "20-24", "gender": "男"}
{"image": "4074.png", "category": "16-19", "gender": "男"}
{"image": "4075.png", "category": "20-24", "gender": "男"}
{"image": "4076.png", "category": "20-24", "gender": "男"}
{"image": "4077.png", "category": "16-19", "gender": "男"}
{"image": "4078.png", "category": "16-19", "gender": "男"}
{"image": "4079.png", "category": "16-19", "gender": "男"}
{"image": "408.png", "category": "16-19", "gender": "男"}
{"image": "4080.png", "category": "16-19", "gender": "男"}
{"image": "4081.png", "category": "16-19", "gender": "男"}
{"image": "4082.png", "category": "13-15", "gender": "男"}
{"image": "4083.png", "category": "13-15", "gender": "男"}
{"image": "4084.png", "category": "13-15", "gender": "男"}
{"image": "4085.png", "category": "16-19", "gender": "男"}
{"image": "4086.png", "category": "20-24", "gender": "男"}
{"image": "4087.png", "category": "25-30", "gender": "男"}
{"image": "4088.png", "category": "16-19", "gender": "男"}
{"image": "4089.png", "category": "16-19", "gender": "男"}
{"image": "409.png", "category": "16-19", "gender": "男"}
{"image": "4090.png", "category": "16-19", "gender": "男"}
{"image": "4091.png", "category": "20-24", "gender": "男"}
{"image": "4092.png", "category": "16-19", "gender": "男"}
{"image": "4093.png", "category": "20-24", "gender": "男"}
{"image": "4094.png", "category": "16-19", "gender": "男"}
{"image": "4095.png", "category": "16-19", "gender": "男"}
{"image": "4096.png", "category": "16-19", "gender": "男"}
{"image": "4097.png", "category": "16-19", "gender": "男"}
{"image": "4098.png", "category": "16-19", "gender": "男"}
{"image": "4099.png", "category": "16-19", "gender": "男"}
{"image": "41.png", "category": "20-24", "gender": "男"}
{"image": "410.png", "category": "20-24", "gender": "男"}
{"image": "4100.png", "category": "20-24", "gender": "男"}
{"image": "4101.png", "category": "20-24", "gender": "男"}
{"image": "4102.png", "category": "20-24", "gender": "男"}
{"image": "4103.png", "category": "13-15", "gender": "男"}
{"image": "4104.png", "category": "13-15", "gender": "男"}
{"image": "4105.png", "category": "13-15", "gender": "男"}
{"image": "4106.png", "category": "16-19", "gender": "男"}
{"image": "4107.png", "category": "16-19", "gender": "男"}
{"image": "4108.png", "category": "16-19", "gender": "男"}
{"image": "4109.png", "category": "13-15", "gender": "男"}
{"image": "411.png", "category": "13-15", "gender": "男"}
{"image": "4110.png", "category": "13-15", "gender": "男"}
{"image": "4111.png", "category": "13-15", "gender": "男"}
{"image": "4112.png", "category": "13-15", "gender": "男"}
{"image": "4113.png", "category": "13-15", "gender": "男"}
{"image": "4114.png", "category": "13-15", "gender": "男"}
{"image": "4115.png", "category": "13-15", "gender": "男"}
{"image": "4116.png", "category": "16-19", "gender": "男"}
{"image": "4117.png", "category": "13-15", "gender": "男"}
